{
  "numFailedTestSuites": 1,
  "numFailedTests": 1,
  "numPassedTestSuites": 0,
  "numPassedTests": 0,
  "numPendingTestSuites": 0,
  "numPendingTests": 3,
  "numRuntimeErrorTestSuites": 0,
  "numTodoTests": 0,
  "numTotalTestSuites": 1,
  "numTotalTests": 4,
  "openHandles": [],
  "snapshot": {
    "added": 0,
    "didUpdate": false,
    "failure": false,
    "filesAdded": 0,
    "filesRemoved": 0,
    "filesRemovedList": [],
    "filesUnmatched": 0,
    "filesUpdated": 0,
    "matched": 0,
    "total": 0,
    "unchecked": 0,
    "uncheckedKeysByFile": [],
    "unmatched": 0,
    "updated": 0
  },
  "startTime": 1602578800337,
  "success": false,
  "testResults": [
    {
      "failureMessage": "\u001b[1m\u001b[31m  \u001b[1m● \u001b[1me2e testing › optimal ss\u001b[39m\u001b[22m\n\n    TimeoutError: While navigating to https://www.milo.co.id/sarapan-untuk-raih-lebih: Navigation timeout of 30000 ms exceeded\n\u001b[2m\u001b[22m\n\u001b[2m    \u001b[0m \u001b[90m 143 | \u001b[39m               \u001b[36mwhile\u001b[39m(i\u001b[33m<=\u001b[39murl\u001b[33m.\u001b[39mlength\u001b[33m-\u001b[39m\u001b[35m1\u001b[39m) {\u001b[0m\u001b[22m\n\u001b[2m    \u001b[0m \u001b[90m 144 | \u001b[39m                 console\u001b[33m.\u001b[39mlog(url[i])\u001b[0m\u001b[22m\n\u001b[2m    \u001b[0m\u001b[31m\u001b[1m>\u001b[2m\u001b[39m\u001b[90m 145 | \u001b[39m                 await page\u001b[33m.\u001b[39mgoto(url[i]\u001b[33m,\u001b[39m {waitUntil\u001b[33m:\u001b[39m \u001b[32m'domcontentloaded'\u001b[39m})\u001b[33m;\u001b[39m\u001b[0m\u001b[22m\n\u001b[2m    \u001b[0m \u001b[90m     | \u001b[39m                 \u001b[31m\u001b[1m^\u001b[2m\u001b[39m\u001b[0m\u001b[22m\n\u001b[2m    \u001b[0m \u001b[90m 146 | \u001b[39m                 await init\u001b[33m.\u001b[39moptmimal_ss(folder_name\u001b[33m,\u001b[39mdevice\u001b[33m.\u001b[39mname\u001b[33m,\u001b[39mi\u001b[33m+\u001b[39murl[i]\u001b[33m.\u001b[39msplit(\u001b[35m/[,\\/:.?]/g\u001b[39m)\u001b[33m,\u001b[39mdevice\u001b[33m.\u001b[39mviewport\u001b[33m.\u001b[39mwidth\u001b[33m,\u001b[39mdevice\u001b[33m.\u001b[39mviewport\u001b[33m.\u001b[39mheight\u001b[33m,\u001b[39mbrowserType)\u001b[33m;\u001b[39m\u001b[0m\u001b[22m\n\u001b[2m    \u001b[0m \u001b[90m 147 | \u001b[39m                 i \u001b[33m=\u001b[39m i \u001b[33m+\u001b[39m \u001b[35m1\u001b[39m\u001b[33m;\u001b[39m\u001b[0m\u001b[22m\n\u001b[2m    \u001b[0m \u001b[90m 148 | \u001b[39m               }\u001b[0m\u001b[22m\n\u001b[2m\u001b[22m\n\u001b[2m      \u001b[2mat throwIfError (\u001b[2mnode_modules/playwright-core/lib/frames.js\u001b[2m:329:23)\u001b[2m\u001b[22m\n\u001b[2m      \u001b[2mat Frame.goto (\u001b[2mnode_modules/playwright-core/lib/frames.js\u001b[2m:307:9)\u001b[2m\u001b[22m\n\u001b[2m      \u001b[2mat \u001b[2m\u001b[0m\u001b[36mtest/projects/scr/scr.test.js\u001b[39m\u001b[0m\u001b[2m:145:18\u001b[2m\u001b[22m\n\u001b[2m      \u001b[2mat Object.<anonymous> (\u001b[2m\u001b[0m\u001b[36mtest/projects/scr/scr.test.js\u001b[39m\u001b[0m\u001b[2m:127:13)\u001b[2m\u001b[22m\n\u001b[2m        -- ASYNC --\u001b[22m\n\u001b[2m      \u001b[2mat Frame.<anonymous> (\u001b[2mnode_modules/playwright-core/lib/helper.js\u001b[2m:54:23)\u001b[2m\u001b[22m\n\u001b[2m      \u001b[2mat Page.goto (\u001b[2mnode_modules/playwright-core/lib/page.js\u001b[2m:224:33)\u001b[2m\u001b[22m\n\u001b[2m      \u001b[2mat Page.goto (\u001b[2mnode_modules/playwright-core/lib/helper.js\u001b[2m:55:31)\u001b[2m\u001b[22m\n\u001b[2m      \u001b[2mat \u001b[2m\u001b[0m\u001b[36mtest/projects/scr/scr.test.js\u001b[39m\u001b[0m\u001b[2m:145:29\u001b[2m\u001b[22m\n\u001b[2m      \u001b[2mat Object.<anonymous> (\u001b[2m\u001b[0m\u001b[36mtest/projects/scr/scr.test.js\u001b[39m\u001b[0m\u001b[2m:127:13)\u001b[2m\u001b[22m\n",
      "numFailingTests": 1,
      "numPassingTests": 0,
      "numPendingTests": 3,
      "numTodoTests": 0,
      "perfStats": {
        "end": 1602579015311,
        "start": 1602578806564
      },
      "snapshot": {
        "added": 0,
        "fileDeleted": false,
        "matched": 0,
        "unchecked": 0,
        "unmatched": 0,
        "updated": 0,
        "uncheckedKeys": []
      },
      "testFilePath": "C:\\Users\\Fajri\\Documents\\automation\\test\\projects\\scr\\scr.test.js",
      "testResults": [
        {
          "ancestorTitles": [
            "e2e testing"
          ],
          "duration": 185227,
          "failureMessages": [
            "TimeoutError: While navigating to https://www.milo.co.id/sarapan-untuk-raih-lebih: Navigation timeout of 30000 ms exceeded\n    at throwIfError (C:\\Users\\Fajri\\Documents\\automation\\node_modules\\playwright-core\\lib\\frames.js:329:23)\n    at Frame.goto (C:\\Users\\Fajri\\Documents\\automation\\node_modules\\playwright-core\\lib\\frames.js:307:9)\n    at C:\\Users\\Fajri\\Documents\\automation\\test\\projects\\scr\\scr.test.js:145:18\n    at Object.<anonymous> (C:\\Users\\Fajri\\Documents\\automation\\test\\projects\\scr\\scr.test.js:127:13)\n  -- ASYNC --\n    at Frame.<anonymous> (C:\\Users\\Fajri\\Documents\\automation\\node_modules\\playwright-core\\lib\\helper.js:54:23)\n    at Page.goto (C:\\Users\\Fajri\\Documents\\automation\\node_modules\\playwright-core\\lib\\page.js:224:33)\n    at Page.goto (C:\\Users\\Fajri\\Documents\\automation\\node_modules\\playwright-core\\lib\\helper.js:55:31)\n    at C:\\Users\\Fajri\\Documents\\automation\\test\\projects\\scr\\scr.test.js:145:29\n    at Object.<anonymous> (C:\\Users\\Fajri\\Documents\\automation\\test\\projects\\scr\\scr.test.js:127:13)"
          ],
          "fullName": "e2e testing optimal ss",
          "location": null,
          "numPassingAsserts": 0,
          "status": "failed",
          "title": "optimal ss"
        },
        {
          "ancestorTitles": [
            "e2e testing"
          ],
          "duration": 1,
          "failureMessages": [],
          "fullName": "e2e testing test performance in mobile",
          "location": null,
          "numPassingAsserts": 0,
          "status": "pending",
          "title": "test performance in mobile"
        },
        {
          "ancestorTitles": [
            "e2e testing"
          ],
          "duration": 0,
          "failureMessages": [],
          "fullName": "e2e testing test performance in desktop",
          "location": null,
          "numPassingAsserts": 0,
          "status": "pending",
          "title": "test performance in desktop"
        },
        {
          "ancestorTitles": [
            "e2e testing"
          ],
          "duration": 0,
          "failureMessages": [],
          "fullName": "e2e testing convert to excel",
          "location": null,
          "numPassingAsserts": 0,
          "status": "pending",
          "title": "convert to excel"
        }
      ],
      "skipped": false,
      "leaks": false
    }
  ],
  "wasInterrupted": false
}